my_logger/__init__.py
my_logger/logger.py
sonic182_my_logger-0.0.3.dist-info/DESCRIPTION.rst
sonic182_my_logger-0.0.3.dist-info/METADATA
sonic182_my_logger-0.0.3.dist-info/RECORD
sonic182_my_logger-0.0.3.dist-info/WHEEL
sonic182_my_logger-0.0.3.dist-info/metadata.json
sonic182_my_logger-0.0.3.dist-info/top_level.txt
