Metadata-Version: 2.0
Name: sonic182-my-logger
Version: 0.0.3
Summary: Logger utilities for aiohttp
Home-page: UNKNOWN
Author: Johanderson Mogollon
Author-email: johanderson@mogollon.com.ve
License: MIT
Platform: UNKNOWN
Provides-Extra: dev
Requires-Dist: aiohttp (==2.2.5); extra == 'dev'
Requires-Dist: astroid (==1.5.3); extra == 'dev'
Requires-Dist: async-timeout (==1.4.0); extra == 'dev'
Requires-Dist: autopep8 (==1.3.2); extra == 'dev'
Requires-Dist: certifi (==2017.7.27.1); extra == 'dev'
Requires-Dist: chardet (==3.0.4); extra == 'dev'
Requires-Dist: coverage (==4.4.1); extra == 'dev'
Requires-Dist: coveralls (==1.2.0); extra == 'dev'
Requires-Dist: docopt (==0.6.2); extra == 'dev'
Requires-Dist: flake8-docstrings (==1.1.0); extra == 'dev'
Requires-Dist: flake8-polyfill (==1.0.1); extra == 'dev'
Requires-Dist: flake8 (==3.4.1); extra == 'dev'
Requires-Dist: greenlet (==0.4.12); extra == 'dev'
Requires-Dist: idna (==2.6); extra == 'dev'
Requires-Dist: isort (==4.2.15); extra == 'dev'
Requires-Dist: jedi (==0.11.0); extra == 'dev'
Requires-Dist: lazy-object-proxy (==1.3.1); extra == 'dev'
Requires-Dist: mccabe (==0.6.1); extra == 'dev'
Requires-Dist: msgpack-python (==0.4.8); extra == 'dev'
Requires-Dist: multidict (==3.2.0); extra == 'dev'
Requires-Dist: neovim (==0.1.13); extra == 'dev'
Requires-Dist: parso (==0.1.0); extra == 'dev'
Requires-Dist: py (==1.4.34); extra == 'dev'
Requires-Dist: pycodestyle (==2.3.1); extra == 'dev'
Requires-Dist: pydocstyle (==2.0.0); extra == 'dev'
Requires-Dist: pyflakes (==1.5.0); extra == 'dev'
Requires-Dist: pylint (==1.7.4); extra == 'dev'
Requires-Dist: pytest-aiohttp (==0.1.3); extra == 'dev'
Requires-Dist: pytest-cov (==2.5.1); extra == 'dev'
Requires-Dist: pytest-sugar (==0.9.0); extra == 'dev'
Requires-Dist: pytest (==3.2.2); extra == 'dev'
Requires-Dist: requests (==2.18.4); extra == 'dev'
Requires-Dist: six (==1.11.0); extra == 'dev'
Requires-Dist: snowballstemmer (==1.2.1); extra == 'dev'
Requires-Dist: termcolor (==1.1.0); extra == 'dev'
Requires-Dist: urllib3 (==1.22); extra == 'dev'
Requires-Dist: wrapt (==1.10.11); extra == 'dev'
Requires-Dist: yarl (==0.12.0); extra == 'dev'
Provides-Extra: test
Requires-Dist: pytest; extra == 'test'
Requires-Dist: coverage; extra == 'test'
Requires-Dist: aiohttp; extra == 'test'
